.gitignore
MANIFEST.in
README.md
requirements.in
requirements.txt
requirements_dev.txt
setup.cfg
setup.py
agconnect/__init__.py
agconnect.egg-info/PKG-INFO
agconnect.egg-info/SOURCES.txt
agconnect.egg-info/dependency_links.txt
agconnect.egg-info/requires.txt
agconnect.egg-info/top_level.txt
agconnect/auth_server/__init__.py
agconnect/auth_server/agconnect_auth.json
agconnect/auth_server/pytest.ini
agconnect/auth_server/src/__init__.py
agconnect/auth_server/src/backend/__init__.py
agconnect/auth_server/src/backend/auth_backend.py
agconnect/auth_server/src/entity/__init__.py
agconnect/auth_server/src/entity/auth_access_token.py
agconnect/auth_server/src/entity/provider.py
agconnect/auth_server/src/entity/token_provider_info.py
agconnect/auth_server/src/entity/user_import_export_result.py
agconnect/auth_server/src/error/__init__.py
agconnect/auth_server/src/error/agc_auth_error_message.py
agconnect/auth_server/src/error/agc_auth_exception.py
agconnect/auth_server/src/jwt/__init__.py
agconnect/auth_server/src/jwt/agc_auth_jwt.py
agconnect/auth_server/src/jwt/agc_auth_jwttoken.py
agconnect/auth_server/src/jwt/agc_auth_public_key_manager.py
agconnect/auth_server/src/jwt/agc_auth_rsa_verifier.py
agconnect/auth_server/src/jwt/rsa_key_pair.py
agconnect/auth_server/src/request/__init__.py
agconnect/auth_server/src/request/export_user_list_req.py
agconnect/auth_server/src/request/export_user_req.py
agconnect/auth_server/src/request/import_export_user_info.py
agconnect/auth_server/src/request/import_user_req.py
agconnect/auth_server/src/request/provider_info.py
agconnect/auth_server/src/request/public_key_req.py
agconnect/auth_server/src/request/revoke_token_req.py
agconnect/auth_server/src/request/verify_token_req.py
agconnect/auth_server/src/response/__init__.py
agconnect/auth_server/src/response/auth_operate_rsp.py
agconnect/auth_server/src/response/export_user_list_rsp.py
agconnect/auth_server/src/response/export_user_rsp.py
agconnect/auth_server/src/response/import_success_user.py
agconnect/auth_server/src/response/import_user_rsp.py
agconnect/auth_server/src/response/publickey_rsp.py
agconnect/auth_server/src/response/token_info.py
