Metadata-Version: 2.1
Name: agconnect
Version: 1.3.0.300
Summary: AppGallery Connect Server-SDK for Python development
Home-page: https://developer.huawei.com/consumer/en/service/josp/agc/index.html,,AppGalleryConnect#/
Author: AppGallery Connect
License: ISC
Project-URL: Documentation, https://github.com/AppGalleryConnect/agc-server-demos-python
Project-URL: Source, https://pypi.org/project/agconnect
Project-URL: Tracker, https://github.com/AppGalleryConnect/agc-server-demos-python/issues
Keywords: agconnect,server SDK,Python,authentication
Platform: UNKNOWN
Requires-Python: >=3.7
